cee_formatter.py
cee_formatter-0.4.1.dist-info/DESCRIPTION.rst
cee_formatter-0.4.1.dist-info/METADATA
cee_formatter-0.4.1.dist-info/RECORD
cee_formatter-0.4.1.dist-info/WHEEL
cee_formatter-0.4.1.dist-info/metadata.json
cee_formatter-0.4.1.dist-info/pbr.json
cee_formatter-0.4.1.dist-info/top_level.txt
