Metadata-Version: 2.0
Name: cee-formatter
Version: 0.4.1
Summary: CEE logging module formatter
Home-page: https://github.com/urbaniak/cee-formatter
Author: Krzysztof Urbaniak
Author-email: krzysztof@urbaniak.co
License: BSD
Platform: UNKNOWN
Classifier: Intended Audience :: Developers
Classifier: Operating System :: OS Independent
Classifier: Programming Language :: Python
